muaddib/__init__.py
muaddib/context_reducer.py
muaddib/history.py
muaddib/main.py
muaddib/message_logging.py
muaddib/paths.py
muaddib/rate_limiter.py
muaddib/agentic_actor/__init__.py
muaddib/agentic_actor/actor.py
muaddib/agentic_actor/tools.py
muaddib/chronicler/__init__.py
muaddib/chronicler/chapters.py
muaddib/chronicler/chronicle.py
muaddib/chronicler/quests.py
muaddib/chronicler/tools.py
muaddib/providers/__init__.py
muaddib/providers/anthropic.py
muaddib/providers/openai.py
muaddib/rooms/__init__.py
muaddib/rooms/autochronicler.py
muaddib/rooms/command.py
muaddib/rooms/message.py
muaddib/rooms/proactive.py
muaddib/rooms/discord/__init__.py
muaddib/rooms/discord/monitor.py
muaddib/rooms/irc/__init__.py
muaddib/rooms/irc/monitor.py
muaddib/rooms/irc/varlink.py
muaddib/rooms/slack/__init__.py
muaddib/rooms/slack/monitor.py
muaddib-1.1.2.dist-info/METADATA
muaddib-1.1.2.dist-info/WHEEL
muaddib-1.1.2.dist-info/entry_points.txt
muaddib-1.1.2.dist-info/licenses/LICENSE
muaddib-1.1.2.dist-info/RECORD
