Metadata-Version: 2.4
Name: muaddib
Version: 1.1.2
Summary: A secure, multi-user AI agent for IRC, Discord, and Slack
Project-URL: Homepage, https://github.com/pasky/muaddib
Project-URL: Repository, https://github.com/pasky/muaddib
Project-URL: Issues, https://github.com/pasky/muaddib/issues
Author-email: pasky <pasky@ucw.cz>
License: MIT
License-File: LICENSE
Requires-Python: >=3.11
Requires-Dist: aiohttp>=3.9.0
Requires-Dist: aiosqlite>=0.19.0
Requires-Dist: ddgs>=0.1.0
Requires-Dist: discord-py>=2.4.0
Requires-Dist: e2b-code-interpreter<2
Requires-Dist: markdownify>=0.11.0
Requires-Dist: openai>=1.40.0
Requires-Dist: slack-bolt>=1.20.0
Requires-Dist: slack-sdk>=3.26.0
Provides-Extra: dev
Requires-Dist: pre-commit>=3.0.0; extra == 'dev'
Requires-Dist: pyright>=1.1.0; extra == 'dev'
Requires-Dist: pytest-asyncio>=0.21.0; extra == 'dev'
Requires-Dist: pytest>=7.0.0; extra == 'dev'
Requires-Dist: ruff>=0.1.0; extra == 'dev'
